.DS_Store
Topsis_Sumit_Garg_102203514/__main__.py
Topsis_Sumit_Garg_102203514/topsis.py
Topsis_Sumit_Garg_102203514-0.1.3.dist-info/LICENSE
Topsis_Sumit_Garg_102203514-0.1.3.dist-info/METADATA
Topsis_Sumit_Garg_102203514-0.1.3.dist-info/WHEEL
Topsis_Sumit_Garg_102203514-0.1.3.dist-info/entry_points.txt
Topsis_Sumit_Garg_102203514-0.1.3.dist-info/top_level.txt
Topsis_Sumit_Garg_102203514-0.1.3.dist-info/RECORD
