Metadata-Version: 2.2
Name: Topsis_Sumit_Garg_102203514
Version: 0.1.3
Summary: A Python package for TOPSIS calculation
Home-page: https://github.com/yourusername/topsis-calculator
Author: Sumit Garg
Author-email: sumit0000garg@gmail.com
Classifier: Programming Language :: Python :: 3
Classifier: License :: OSI Approved :: MIT License
Classifier: Operating System :: OS Independent
Requires-Python: >=3.6
License-File: LICENSE
Requires-Dist: numpy
Requires-Dist: pandas
Dynamic: author
Dynamic: author-email
Dynamic: classifier
Dynamic: description
Dynamic: description-content-type
Dynamic: home-page
Dynamic: requires-dist
Dynamic: requires-python
Dynamic: summary
